LICENSE
MANIFEST.in
README.md
setup.py
sensorAtlas/__init__.py
sensorAtlas/apps.py
sensorAtlas/errors.py
sensorAtlas/functions.py
sensorAtlas/mixins.py
sensorAtlas/models.py
sensorAtlas/pagination.py
sensorAtlas/parsers.py
sensorAtlas/router.py
sensorAtlas/routers.py
sensorAtlas/serializer.py
sensorAtlas/urls.py
sensorAtlas/utils.py
sensorAtlas/views.py
sensorAtlas/viewsets.py
sensorAtlas.egg-info/PKG-INFO
sensorAtlas.egg-info/SOURCES.txt
sensorAtlas.egg-info/dependency_links.txt
sensorAtlas.egg-info/requires.txt
sensorAtlas.egg-info/top_level.txt
tests/__init__.py
tests/models.py
tests/test_complianceA1.py
tests/test_complianceA2.py
tests/test_complianceA3.py
tests/test_complianceA4.py
tests/test_complianceA6.py
tests/test_settings.py
tests/urls.py
tests/wsgi.py
tests/__pycache__/__init__.cpython-310.pyc
tests/__pycache__/test_complianceA1.cpython-310.pyc
tests/__pycache__/test_complianceA2.cpython-310.pyc
tests/__pycache__/test_complianceA3.cpython-310.pyc
tests/__pycache__/test_complianceA4.cpython-310.pyc
tests/__pycache__/test_complianceA6.cpython-310.pyc
tests/__pycache__/test_settings.cpython-310.pyc
tests/__pycache__/urls.cpython-310.pyc